sqlglot/__init__.py
sqlglot/__main__.py
sqlglot/_typing.py
sqlglot/_version.py
sqlglot/diff.py
sqlglot/errors.py
sqlglot/expressions.py
sqlglot/generator.py
sqlglot/helper.py
sqlglot/jsonpath.py
sqlglot/lineage.py
sqlglot/parser.py
sqlglot/planner.py
sqlglot/py.typed
sqlglot/schema.py
sqlglot/serde.py
sqlglot/time.py
sqlglot/tokens.py
sqlglot/transforms.py
sqlglot/trie.py
sqlglot/dialects/__init__.py
sqlglot/dialects/athena.py
sqlglot/dialects/bigquery.py
sqlglot/dialects/clickhouse.py
sqlglot/dialects/databricks.py
sqlglot/dialects/dialect.py
sqlglot/dialects/doris.py
sqlglot/dialects/dremio.py
sqlglot/dialects/drill.py
sqlglot/dialects/druid.py
sqlglot/dialects/duckdb.py
sqlglot/dialects/dune.py
sqlglot/dialects/exasol.py
sqlglot/dialects/fabric.py
sqlglot/dialects/hive.py
sqlglot/dialects/materialize.py
sqlglot/dialects/mysql.py
sqlglot/dialects/oracle.py
sqlglot/dialects/postgres.py
sqlglot/dialects/presto.py
sqlglot/dialects/prql.py
sqlglot/dialects/redshift.py
sqlglot/dialects/risingwave.py
sqlglot/dialects/singlestore.py
sqlglot/dialects/snowflake.py
sqlglot/dialects/solr.py
sqlglot/dialects/spark.py
sqlglot/dialects/spark2.py
sqlglot/dialects/sqlite.py
sqlglot/dialects/starrocks.py
sqlglot/dialects/tableau.py
sqlglot/dialects/teradata.py
sqlglot/dialects/timeplus.py
sqlglot/dialects/trino.py
sqlglot/dialects/tsql.py
sqlglot/executor/__init__.py
sqlglot/executor/context.py
sqlglot/executor/env.py
sqlglot/executor/python.py
sqlglot/executor/table.py
sqlglot/optimizer/__init__.py
sqlglot/optimizer/annotate_types.py
sqlglot/optimizer/canonicalize.py
sqlglot/optimizer/eliminate_ctes.py
sqlglot/optimizer/eliminate_joins.py
sqlglot/optimizer/eliminate_subqueries.py
sqlglot/optimizer/isolate_table_selects.py
sqlglot/optimizer/merge_subqueries.py
sqlglot/optimizer/normalize.py
sqlglot/optimizer/normalize_identifiers.py
sqlglot/optimizer/optimize_joins.py
sqlglot/optimizer/optimizer.py
sqlglot/optimizer/pushdown_predicates.py
sqlglot/optimizer/pushdown_projections.py
timeplus_sqlglot-0.1.0.dist-info/licenses/LICENSE
timeplus_sqlglot-0.1.0.dist-info/METADATA
timeplus_sqlglot-0.1.0.dist-info/WHEEL
timeplus_sqlglot-0.1.0.dist-info/top_level.txt
timeplus_sqlglot-0.1.0.dist-info/RECORD
