Metadata-Version: 2.4
Name: timeplus-sqlglot
Version: 0.1.0
Summary: An easily customizable SQL parser and transpiler with Timeplus streaming SQL dialect support
Author-email: timeplus-yokofly <haohang.shi@timeplus.io>
Maintainer-email: "Timeplus Inc." <eng@timeplus.com>
License-Expression: MIT
Project-URL: Homepage, https://github.com/timeplus-io/sqlglot
Project-URL: Documentation, https://github.com/timeplus-io/sqlglot/tree/main
Project-URL: Repository, https://github.com/timeplus-io/sqlglot
Project-URL: Issues, https://github.com/timeplus-io/sqlglot/issues
Project-URL: Organization, https://pypi.org/user/timeplus/
Classifier: Development Status :: 4 - Beta
Classifier: Intended Audience :: Developers
Classifier: Intended Audience :: Science/Research
Classifier: Operating System :: OS Independent
Classifier: Programming Language :: SQL
Classifier: Programming Language :: Python :: 3 :: Only
Requires-Python: >=3.9
License-File: LICENSE
Provides-Extra: dev
Requires-Dist: duckdb>=0.6; extra == "dev"
Requires-Dist: mypy; extra == "dev"
Requires-Dist: pandas; extra == "dev"
Requires-Dist: pandas-stubs; extra == "dev"
Requires-Dist: python-dateutil; extra == "dev"
Requires-Dist: pytz; extra == "dev"
Requires-Dist: pdoc; extra == "dev"
Requires-Dist: pre-commit; extra == "dev"
Requires-Dist: ruff==0.7.2; extra == "dev"
Requires-Dist: types-python-dateutil; extra == "dev"
Requires-Dist: types-pytz; extra == "dev"
Requires-Dist: typing_extensions; extra == "dev"
Requires-Dist: maturin<2.0,>=1.4; extra == "dev"
Requires-Dist: pyperf; extra == "dev"
Provides-Extra: rs
Requires-Dist: sqlglotrs==0.6.2; extra == "rs"
Dynamic: license-file
Dynamic: provides-extra
